{
    "services": [
        {    
            "id": 1,
            "title": "PLUMBING",
            "img": "images/plumbing.jpg"    
        },

        {
            "id": 2,
            "title": "ELECTRICIAN",
            "img": "images/Electrician.jpg"   
        },

        {
            "id": 3,
            "title": "HVAC",
            "img": "images/heater.jpg"   
        },

        {   "id": 4,
            "title": "REMODELING",
            "img": "images/remodeling.jpg" 

        }
        
    ]
}